LICENSE
README.md
setup.py
disstat/__init__.py
disstat/main.py
disstat.py.egg-info/PKG-INFO
disstat.py.egg-info/SOURCES.txt
disstat.py.egg-info/dependency_links.txt
disstat.py.egg-info/requires.txt
disstat.py.egg-info/top_level.txt