Metadata-Version: 2.1
Name: disstat.py
Version: 0.0.1
Summary: disstat.py is a python library for DisStat
Home-page: https://github.com/thedtvn/disstat.py
Author: The DT
License: Apache License 2.0
License-File: LICENSE
Requires-Dist: aiohttp
Requires-Dist: psutil
Requires-Dist: setuptools
Requires-Dist: discord
